cs/app/dlog.py
cs.app.dlog-20240316.dist-info/METADATA
cs.app.dlog-20240316.dist-info/WHEEL
cs.app.dlog-20240316.dist-info/entry_points.txt
cs.app.dlog-20240316.dist-info/top_level.txt
cs.app.dlog-20240316.dist-info/RECORD
