Metadata-Version: 2.1
Name: cs.app.dlog
Version: 20240316
Summary: Log a line in my daily log.
Author-email: Cameron Simpson <cs@cskk.id.au>
License: GNU General Public License v3 or later (GPLv3+)
Project-URL: URL, https://bitbucket.org/cameron_simpson/css/commits/all
Keywords: python3
Platform: UNKNOWN
Classifier: Programming Language :: Python
Classifier: Programming Language :: Python :: 3
Classifier: Development Status :: 5 - Production/Stable
Classifier: Environment :: Console
Classifier: Intended Audience :: Developers
Classifier: Topic :: System :: Logging
Classifier: Topic :: Utilities
Classifier: Operating System :: OS Independent
Classifier: License :: OSI Approved :: GNU General Public License v3 or later (GPLv3+)
Requires-Dist: arrow
Requires-Dist: cs.buffer >=20240201
Requires-Dist: cs.cmdutils >=20240211
Requires-Dist: cs.context >=20240212.1
Requires-Dist: cs.dateutils >=20230210
Requires-Dist: cs.deco >=20240316
Requires-Dist: cs.fstags >=20240211
Requires-Dist: cs.lex >=20240211
Requires-Dist: cs.logutils >=20230212
Requires-Dist: cs.pfx >=20230604
Requires-Dist: cs.progress >=20230401
Requires-Dist: cs.queues >=20240305
Requires-Dist: cs.resources >=20240201
Requires-Dist: cs.sqltags >=20240305
Requires-Dist: cs.tagset >=20240305
Requires-Dist: cs.upd >=20240216
Requires-Dist: icontract
Requires-Dist: typeguard
